pymecompress/__init__.py
pymecompress/bcl.cp39-win_amd64.pyd
pymecompress/codecs.py
pymecompress/cython_numpy_monkey.py
pymecompress/setup.py
pymecompress/version.py
pymecompress-0.3.6.dist-info/LICENSE
pymecompress-0.3.6.dist-info/METADATA
pymecompress-0.3.6.dist-info/WHEEL
pymecompress-0.3.6.dist-info/top_level.txt
pymecompress-0.3.6.dist-info/RECORD
