Metadata-Version: 2.1
Name: pymecompress
Version: 0.3.6
Summary: Compression for photon-noise limited images which keeps losses within the Poisson noise envelope
Home-page: https://github.com/python-microscopy/pymecompress
Author: David Baddeley
Author-email: David Baddeley <d.baddeley@auckland.ac.nz>
License: BSD
Project-URL: Homepage, https://github.com/python-microscopy/pymecompress
Classifier: Programming Language :: Python :: 3
Classifier: License :: OSI Approved :: BSD License
Classifier: Operating System :: OS Independent
Requires-Python: >=3.6
License-File: LICENSE
Requires-Dist: numpy
